{
  "name": "Forgot Password",
  "request": {
    "type": "http",
    "url": "{{baseUrl}}/api/user/forgot-password",
    "scripts": {
      "preRequest": "",
      "postResponse": "if (rq.response.code === 200) {\n    var jsonData = rq.response.json();\n    if (jsonData.resetToken) {\n        rq.environment.set('resetToken', jsonData.resetToken);\n        var email = rq.request.body.urlencoded ? rq.request.body.urlencoded.get('email') : (rq.request.body.raw ? JSON.parse(rq.request.body.raw).email : '');\n        if (email) {\n            rq.environment.set('userEmail', email);\n        }\n        console.log('Reset Token saved:', jsonData.resetToken);\n    }\n}"
    },
    "method": "POST",
    "queryParams": [],
    "headers": [
      {
        "id": 0,
        "key": "Content-Type",
        "value": "application/json",
        "isEnabled": true
      }
    ],
    "body": "{\n  \"email\": \"admin@jewelrystore.com\"\n}",
    "bodyContainer": {
      "text": "{\n  \"email\": \"admin@jewelrystore.com\"\n}"
    },
    "contentType": "text/plain",
    "auth": {
      "currentAuthType": "INHERIT",
      "authConfigStore": {}
    }
  }
}